{
  "$schema": "https://json-schema.org/draft/2020-12/schema",
  "$id": "https://github.com/brettinternet/stream-deck-hammerspoon/protocol/schema/protocol-v1.json",
  "title": "Stream Deck–Hammerspoon protocol v1",
  "description": "Canonical wire schema for authenticated Stream Deck–Hammerspoon messages.",
  "oneOf": [
    { "$ref": "#/$defs/hello" },
    { "$ref": "#/$defs/helloAck" },
    { "$ref": "#/$defs/listActions" },
    { "$ref": "#/$defs/actions" },
    { "$ref": "#/$defs/instanceAppeared" },
    { "$ref": "#/$defs/instanceDisappeared" },
    { "$ref": "#/$defs/keyDown" },
    { "$ref": "#/$defs/keyUp" },
    { "$ref": "#/$defs/dialDown" },
    { "$ref": "#/$defs/dialRotate" },
    { "$ref": "#/$defs/dialUp" },
    { "$ref": "#/$defs/touchTap" },

    { "$ref": "#/$defs/requestAppearance" },
    { "$ref": "#/$defs/appearance" },
    { "$ref": "#/$defs/feedback" },
    { "$ref": "#/$defs/error" }
  ],
  "$defs": {
    "id": {
      "type": "string",
      "minLength": 1
    },
    "sessionId": {
      "type": "string",
      "minLength": 1,
      "description": "Opaque, non-empty server-generated identity for the current authenticated WebSocket session."
    },
    "text": {
      "type": "string",
      "minLength": 1
    },
    "descriptionText": {
      "type": "string",
      "minLength": 1,
      "maxLength": 512,
      "description": "Optional human-readable metadata bounded to 512 Unicode code points."
    },
    "settings": {
      "type": "object",
      "description": "Application-owned JSON object. Keys and values are opaque to protocol v1.",
      "additionalProperties": true
    },
    "deviceMetadata": {
      "type": "object",
      "properties": {
        "controllerType": { "type": "string", "enum": ["keypad", "encoder"] },
        "imageSize": { "type": "integer", "minimum": 1, "maximum": 144 },
        "device": {
          "type": "object",
          "properties": {
            "type": {
              "type": "string",
              "enum": [
                "stream-deck", "stream-deck-mini", "stream-deck-xl", "stream-deck-mobile",
                "corsair-g-keys", "stream-deck-pedal", "corsair-voyager", "stream-deck-plus",
                "scuf-controller", "stream-deck-neo", "stream-deck-studio", "virtual-stream-deck",
                "galleon-100-sd", "stream-deck-plus-xl", "unknown"
              ]
            },
            "size": {
              "type": "object",
              "properties": {
                "columns": { "type": "integer", "minimum": 1, "maximum": 64 },
                "rows": { "type": "integer", "minimum": 1, "maximum": 64 }
              },
              "required": ["columns", "rows"],
              "additionalProperties": false
            }
          },
          "required": ["type", "size"],
          "additionalProperties": false
        }
      },
      "required": ["controllerType", "device"],
      "additionalProperties": false
    },
    "settingsFieldBase": {
      "type": "object",
      "required": ["type", "key"],
      "properties": {
        "type": { "type": "string", "enum": ["text", "number", "boolean", "select"] },
        "key": { "type": "string", "minLength": 1, "maxLength": 64 },
        "label": { "type": "string", "minLength": 1, "maxLength": 128 },
        "description": { "$ref": "#/$defs/descriptionText" },
        "required": { "type": "boolean" },
        "default": {}
      }
    },
    "textSettingsField": {
      "allOf": [
        { "$ref": "#/$defs/settingsFieldBase" },
        {
          "type": "object",
          "properties": {
            "type": { "const": "text" },
            "default": { "type": "string" },
            "minLength": { "type": "integer", "minimum": 0, "maximum": 4096 },
            "maxLength": { "type": "integer", "minimum": 0, "maximum": 4096 }
          }
        }
      ]
    },
    "numberSettingsField": {
      "allOf": [
        { "$ref": "#/$defs/settingsFieldBase" },
        {
          "type": "object",
          "properties": {
            "type": { "const": "number" },
            "default": { "type": "number", "minimum": -1000000000000, "maximum": 1000000000000 },
            "min": { "type": "number", "minimum": -1000000000000, "maximum": 1000000000000 },
            "max": { "type": "number", "minimum": -1000000000000, "maximum": 1000000000000 },
            "step": { "type": "number", "exclusiveMinimum": 0, "maximum": 1000000000000 }
          }
        }
      ]
    },
    "booleanSettingsField": {
      "allOf": [
        { "$ref": "#/$defs/settingsFieldBase" },
        {
          "type": "object",
          "properties": {
            "type": { "const": "boolean" },
            "default": { "type": "boolean" }
          }
        }
      ]
    },
    "selectSettingsField": {
      "allOf": [
        { "$ref": "#/$defs/settingsFieldBase" },
        {
          "type": "object",
          "required": ["options"],
          "properties": {
            "type": { "const": "select" },
            "default": { "type": "string" },
            "options": {
              "type": "array",
              "minItems": 1,
              "maxItems": 64,
              "items": {
                "type": "object",
                "required": ["value", "label"],
                "properties": {
                  "value": { "type": "string", "minLength": 1, "maxLength": 256 },
                  "label": { "type": "string", "minLength": 1, "maxLength": 128 }
                },
                "additionalProperties": false
              }
            }
          }
        }
      ]
    },
    "settingsField": {
      "type": "object",
      "oneOf": [
        { "$ref": "#/$defs/textSettingsField" },
        { "$ref": "#/$defs/numberSettingsField" },
        { "$ref": "#/$defs/booleanSettingsField" },
        { "$ref": "#/$defs/selectSettingsField" }
      ],
      "unevaluatedProperties": false
    },
    "message": {
      "type": "object",
      "required": ["protocolVersion", "type"],
      "properties": {
        "protocolVersion": {
          "type": "integer",
          "const": 1
        },
        "type": {
          "type": "string",
          "minLength": 1
        }
      },
      "additionalProperties": true
    },
    "hello": {
      "allOf": [
        { "$ref": "#/$defs/message" },
        {
          "type": "object",
          "properties": {
            "type": { "const": "hello" },
            "token": { "$ref": "#/$defs/text" },
            "pluginVersion": { "$ref": "#/$defs/text" }
          },
          "required": ["token", "pluginVersion"],
          "additionalProperties": true
        }
      ]
    },
    "helloAck": {
      "allOf": [
        { "$ref": "#/$defs/message" },
        {
          "type": "object",
          "properties": {
            "type": { "const": "helloAck" },
            "sessionId": { "$ref": "#/$defs/sessionId" }
          },
          "required": ["sessionId"],
          "additionalProperties": true
        }
      ]
    },
    "listActions": {
      "allOf": [
        { "$ref": "#/$defs/message" },
        {
          "type": "object",
          "properties": {
            "type": { "const": "listActions" },
            "sessionId": { "$ref": "#/$defs/sessionId" },
            "requestId": { "$ref": "#/$defs/id" }
          },
          "required": ["sessionId", "requestId"],
          "additionalProperties": true
        }
      ]
    },
    "actionDefinition": {
      "type": "object",
      "properties": {
        "actionId": { "$ref": "#/$defs/id" },
        "name": { "$ref": "#/$defs/text" },
        "description": { "$ref": "#/$defs/descriptionText" },
        "settingsSchema": {
          "type": "array",
          "maxItems": 32,
          "items": {},
          "description": "Optional bounded legacy field descriptors; explicit settingsSchemaVersion: 1 enables strict descriptor validation."
        },
        "settingsSchemaVersion": { "type": "integer", "minimum": 1, "maximum": 16 }
      },
      "required": ["actionId", "name"],
      "allOf": [
        {
          "if": { "required": ["settingsSchemaVersion"] },
          "then": { "required": ["settingsSchema"] }
        },
        {
          "if": {
            "properties": { "settingsSchemaVersion": { "const": 1 } },
            "required": ["settingsSchemaVersion"]
          },
          "then": {
            "properties": {
              "settingsSchema": {
                "type": "array",
                "maxItems": 32,
                "items": { "$ref": "#/$defs/settingsField" }
              }
            }
          }
        }
      ],
      "additionalProperties": true
    },
    "actions": {
      "allOf": [
        { "$ref": "#/$defs/message" },
        {
          "type": "object",
          "properties": {
            "type": { "const": "actions" },
            "requestId": { "$ref": "#/$defs/id" },
            "actions": {
              "type": "array",
              "items": { "$ref": "#/$defs/actionDefinition" }
            }
          },
          "required": ["requestId", "actions"],
          "additionalProperties": true
        }
      ]
    },
    "instanceAppeared": {
      "allOf": [
        { "$ref": "#/$defs/message" },
        {
          "type": "object",
          "properties": {
            "type": { "const": "instanceAppeared" },
            "sessionId": { "$ref": "#/$defs/sessionId" },
            "instanceId": { "$ref": "#/$defs/id" },
            "actionId": { "$ref": "#/$defs/id" },
            "settings": { "$ref": "#/$defs/settings" },
            "metadata": { "$ref": "#/$defs/deviceMetadata" }
          },
          "required": ["sessionId", "instanceId", "actionId", "settings"],
          "additionalProperties": true
        }
      ]
    },
    "instanceDisappeared": {
      "allOf": [
        { "$ref": "#/$defs/message" },
        {
          "type": "object",
          "properties": {
            "type": { "const": "instanceDisappeared" },
            "sessionId": { "$ref": "#/$defs/sessionId" },
            "instanceId": { "$ref": "#/$defs/id" },
            "actionId": { "$ref": "#/$defs/id" }
          },
          "required": ["sessionId", "instanceId", "actionId"],
          "additionalProperties": true
        }
      ]
    },
    "keyDown": {
      "allOf": [
        { "$ref": "#/$defs/message" },
        {
          "type": "object",
          "properties": {
            "type": { "const": "keyDown" },
            "sessionId": { "$ref": "#/$defs/sessionId" },
            "instanceId": { "$ref": "#/$defs/id" },
            "actionId": { "$ref": "#/$defs/id" }
          },
          "required": ["sessionId", "instanceId", "actionId"],
          "additionalProperties": true
        }
      ]
    },
    "keyUp": {
      "allOf": [
        { "$ref": "#/$defs/message" },
        {
          "type": "object",
          "properties": {
            "type": { "const": "keyUp" },
            "sessionId": { "$ref": "#/$defs/sessionId" },
            "instanceId": { "$ref": "#/$defs/id" },
            "actionId": { "$ref": "#/$defs/id" }
          },
          "required": ["sessionId", "instanceId", "actionId"],
          "additionalProperties": true
        }
      ]
    },
    "dialDown": {
      "allOf": [
        { "$ref": "#/$defs/message" },
        {
          "type": "object",
          "properties": {
            "type": { "const": "dialDown" },
            "sessionId": { "$ref": "#/$defs/sessionId" },
            "instanceId": { "$ref": "#/$defs/id" },
            "actionId": { "$ref": "#/$defs/id" }
          },
          "required": ["sessionId", "instanceId", "actionId"],
          "additionalProperties": true
        }
      ]
    },
    "dialRotate": {
      "allOf": [
        { "$ref": "#/$defs/message" },
        {
          "type": "object",
          "properties": {
            "type": { "const": "dialRotate" },
            "sessionId": { "$ref": "#/$defs/sessionId" },
            "instanceId": { "$ref": "#/$defs/id" },
            "actionId": { "$ref": "#/$defs/id" },
            "ticks": { "type": "integer" },
            "pressed": { "type": "boolean" }
          },
          "required": ["sessionId", "instanceId", "actionId", "ticks", "pressed"],
          "additionalProperties": true
        }
      ]
    },
    "dialUp": {
      "allOf": [
        { "$ref": "#/$defs/message" },
        {
          "type": "object",
          "properties": {
            "type": { "const": "dialUp" },
            "sessionId": { "$ref": "#/$defs/sessionId" },
            "instanceId": { "$ref": "#/$defs/id" },
            "actionId": { "$ref": "#/$defs/id" }
          },
          "required": ["sessionId", "instanceId", "actionId"],
          "additionalProperties": true
        }
      ]
    },
    "touchTap": {
      "allOf": [
        { "$ref": "#/$defs/message" },
        {
          "type": "object",
          "properties": {
            "type": { "const": "touchTap" },
            "sessionId": { "$ref": "#/$defs/sessionId" },
            "instanceId": { "$ref": "#/$defs/id" },
            "actionId": { "$ref": "#/$defs/id" },
            "hold": { "type": "boolean" },
            "tapPos": {
              "type": "array",
              "prefixItems": [
                { "type": "number", "minimum": 0, "maximum": 800 },
                { "type": "number", "minimum": 0, "maximum": 100 }
              ],
              "items": false,
              "minItems": 2,
              "maxItems": 2
            }
          },
          "required": ["sessionId", "instanceId", "actionId", "hold", "tapPos"],
          "additionalProperties": true
        }
      ]
    },
    "requestAppearance": {
      "allOf": [
        { "$ref": "#/$defs/message" },
        {
          "type": "object",
          "properties": {
            "type": { "const": "requestAppearance" },
            "sessionId": { "$ref": "#/$defs/sessionId" },
            "instanceId": { "$ref": "#/$defs/id" },
            "actionId": { "$ref": "#/$defs/id" }
          },
          "required": ["sessionId", "instanceId", "actionId"],
          "additionalProperties": true
        }
      ]
    },
    "appearanceColor": {
      "type": "string",
      "pattern": "^#[0-9A-Fa-f]{6}$"
    },
    "appearanceBadge": {
      "type": "string",
      "maxLength": 4
    },
    "appearanceValue": {
      "type": "string",
      "minLength": 1,
      "maxLength": 16,
      "pattern": "^[^\\u0000-\\u001F\\u007F-\\u009F]*$"
    },
    "appearanceIndicator": {
      "type": "number",
      "minimum": 0,
      "maximum": 100
    },
    "appearanceIcon": {
      "oneOf": [
        {
          "type": "object",
          "properties": {
            "kind": { "const": "bundled" },
            "name": { "type": "string", "pattern": "^[a-z][a-z0-9-]{0,31}$" }
          },
          "required": ["kind", "name"],
          "additionalProperties": false
        },
        {
          "type": "object",
          "properties": {
            "kind": { "const": "custom" },
            "mediaType": { "type": "string", "enum": ["image/png", "image/svg+xml"] },
            "dataBase64": {
              "type": "string",
              "minLength": 4,
              "maxLength": 43692,
              "pattern": "^(?:[A-Za-z0-9+/]{4})*(?:[A-Za-z0-9+/]{2}==|[A-Za-z0-9+/]{3}=)?$"
            }
          },
          "required": ["kind", "mediaType", "dataBase64"],
          "additionalProperties": false
        }
      ]
    },
    "appearance": {
      "allOf": [
        { "$ref": "#/$defs/message" },
        {
          "type": "object",
          "properties": {
            "type": { "const": "appearance" },
            "instanceId": { "$ref": "#/$defs/id" },
            "actionId": { "$ref": "#/$defs/id" },
            "title": { "type": "string" },
            "state": { "type": "integer", "enum": [0, 1] },
            "appearanceVersion": { "const": 1 },
            "presentationState": { "type": "integer", "minimum": 0, "maximum": 3 },
            "foregroundColor": { "$ref": "#/$defs/appearanceColor" },
            "backgroundColor": { "$ref": "#/$defs/appearanceColor" },
            "progress": { "type": "number", "minimum": 0, "maximum": 1 },
            "badge": { "$ref": "#/$defs/appearanceBadge" },
            "icon": { "$ref": "#/$defs/appearanceIcon" },
            "value": { "$ref": "#/$defs/appearanceValue" },
            "indicator": { "$ref": "#/$defs/appearanceIndicator" }
          },
          "required": ["instanceId", "actionId", "title", "state"],
          "additionalProperties": true
        },
        {
          "if": {
            "type": "object",
            "anyOf": [
              { "required": ["foregroundColor"] },
              { "required": ["backgroundColor"] },
              { "required": ["progress"] },
              { "required": ["badge"] },
              { "required": ["icon"] },
              { "required": ["presentationState"] }
            ]
          },
          "then": { "type": "object", "required": ["appearanceVersion"] }
        },
        {
          "if": {
            "type": "object",
            "anyOf": [
              { "required": ["value"] },
              { "required": ["indicator"] }
            ]
          },
          "then": {
            "type": "object",
            "required": ["appearanceVersion", "value", "indicator"],
            "not": {
              "anyOf": [
                { "required": ["foregroundColor"] },
                { "required": ["backgroundColor"] },
                { "required": ["progress"] },
                { "required": ["badge"] }
              ]
            }
          }
        }
      ]
    },
    "feedback": {
      "allOf": [
        { "$ref": "#/$defs/message" },
        {
          "type": "object",
          "properties": {
            "type": { "const": "feedback" },
            "instanceId": { "$ref": "#/$defs/id" },
            "actionId": { "$ref": "#/$defs/id" },
            "kind": { "type": "string", "enum": ["success", "error"] },
            "message": { "$ref": "#/$defs/feedbackText" },
            "durationMs": { "type": "number", "minimum": 100, "maximum": 10000 }
          },
          "required": ["instanceId", "actionId", "kind", "message", "durationMs"],
          "additionalProperties": true
        }
      ]
    },
    "feedbackText": {
      "type": "string",
      "minLength": 1,
      "maxLength": 256,
      "pattern": "^[^\\u0000-\\u001F\\u007F-\\u009F]+$"
    },
    "error": {
      "allOf": [
        { "$ref": "#/$defs/message" },
        {
          "type": "object",
          "properties": {
            "type": { "const": "error" },
            "code": {
              "type": "string",
              "enum": [
                "AUTH_REQUIRED",
                "AUTH_FAILED",
                "VERSION_MISMATCH",
                "MALFORMED_MESSAGE",
                "UNKNOWN_TYPE",
                "INVALID_FIELD",
                "INVALID_STATE",
                "UNKNOWN_ACTION",
                "STALE_INSTANCE",
                "CALLBACK_FAILED",
                "INTERNAL"
              ]
            },
            "message": { "$ref": "#/$defs/text" },
            "requestId": { "$ref": "#/$defs/id" },
            "instanceId": { "$ref": "#/$defs/id" }
          },
          "required": ["code", "message"],
          "additionalProperties": true
        }
      ]
    }
  }
}
